utils/__init__.py
utils/bot.py
utils/context.py
utils/paginator.py
utils/settings.py
dpy_utils-0.1.0.dist-info/LICENSE
dpy_utils-0.1.0.dist-info/WHEEL
dpy_utils-0.1.0.dist-info/METADATA
dpy_utils-0.1.0.dist-info/RECORD
