Metadata-Version: 2.1
Name: dpy-utils
Version: 0.1.0
Summary: A discord.py utility library.
Home-page: https://github.com/makupi/dpy-utils
License: GPLv3
Author: makubob
Author-email: makupi@icloud.com
Requires-Python: >=3.6,<4.0
Classifier: License :: Other/Proprietary License
Classifier: Programming Language :: Python :: 3
Classifier: Programming Language :: Python :: 3.6
Classifier: Programming Language :: Python :: 3.7
Classifier: Programming Language :: Python :: 3.8
Classifier: Programming Language :: Python :: 3.9
Requires-Dist: pydantic (>=1.7.3,<2.0.0)
Requires-Dist: python-dotenv (>=0.15.0,<0.16.0)
Project-URL: Repository, https://github.com/makupi/dpy-utils
